growthcurves/__init__.py
growthcurves/models.py
growthcurves/non_parametric.py
growthcurves/parametric.py
growthcurves/plot.py
growthcurves/utils.py
growthcurves/__pycache__/__init__.cpython-311.pyc
growthcurves/__pycache__/__init__.cpython-312.pyc
growthcurves/__pycache__/models.cpython-311.pyc
growthcurves/__pycache__/models.cpython-312.pyc
growthcurves/__pycache__/non_parametric.cpython-311.pyc
growthcurves/__pycache__/non_parametric.cpython-312.pyc
growthcurves/__pycache__/parametric.cpython-311.pyc
growthcurves/__pycache__/parametric.cpython-312.pyc
growthcurves/__pycache__/plot.cpython-311.pyc
growthcurves/__pycache__/plot.cpython-312.pyc
growthcurves/__pycache__/utils.cpython-311.pyc
growthcurves/__pycache__/utils.cpython-312.pyc
growthcurves-0.3.0.dist-info/licenses/LICENSE
growthcurves-0.3.0.dist-info/METADATA
growthcurves-0.3.0.dist-info/WHEEL
growthcurves-0.3.0.dist-info/entry_points.txt
growthcurves-0.3.0.dist-info/top_level.txt
growthcurves-0.3.0.dist-info/RECORD
