Metadata-Version: 2.4
Name: growthcurves
Version: 0.3.0
Summary: A package for fitting and analyzing microbial growth curves.
Author-email: Henry Webel <heweb@dtu.dk>, Samuel Bradley <sambra@dtu.dk>
License-Expression: GPL-3.0-or-later
Project-URL: Bug Tracker, https://github.com/biosustain/growthcurves/issues
Project-URL: Homepage, https://github.com/biosustain/growthcurves
Classifier: Programming Language :: Python :: 3
Classifier: Operating System :: OS Independent
Requires-Python: >=3.9
License-File: LICENSE
Requires-Dist: numpy>=1.20.0
Requires-Dist: scipy>=1.7.0
Requires-Dist: plotly>=5.0.0
Provides-Extra: docs
Requires-Dist: sphinx; extra == "docs"
Requires-Dist: sphinx-book-theme; extra == "docs"
Requires-Dist: myst-nb; extra == "docs"
Requires-Dist: ipywidgets; extra == "docs"
Requires-Dist: sphinx-new-tab-link!=0.2.2; extra == "docs"
Requires-Dist: jupytext; extra == "docs"
Requires-Dist: sphinx-copybutton; extra == "docs"
Requires-Dist: plotly; extra == "docs"
Requires-Dist: pandas; extra == "docs"
Requires-Dist: numpy; extra == "docs"
Provides-Extra: dev
Requires-Dist: black[jupyter]; extra == "dev"
Requires-Dist: ruff; extra == "dev"
Requires-Dist: pytest; extra == "dev"
Requires-Dist: isort; extra == "dev"
Requires-Dist: jupytext; extra == "dev"
Dynamic: license-file
